textblob_fr/__init__.py
textblob_fr/_text.py
textblob_fr/compat.py
textblob_fr/fr-context.txt
textblob_fr/fr-lexicon.txt
textblob_fr/fr-morphology.txt
textblob_fr/fr-sentiment.xml
textblob_fr/fr-verbs.txt
textblob_fr/fr.py
textblob_fr/inflect.py
textblob_fr/sentiments.py
textblob_fr/taggers.py
textblob_fr-0.2.0.dist-info/DESCRIPTION.rst
textblob_fr-0.2.0.dist-info/METADATA
textblob_fr-0.2.0.dist-info/pydist.json
textblob_fr-0.2.0.dist-info/RECORD
textblob_fr-0.2.0.dist-info/top_level.txt
textblob_fr-0.2.0.dist-info/WHEEL
