Metadata-Version: 1.1
Name: textblob-fr
Version: 0.2.0
Summary: French language support for TextBlob.
Home-page: https://github.com/sloria/textblob-fr
Author: Steven Loria
Author-email: sloria1@gmail.com
License: Copyright 2013 Steven Loria
